[
    {
        "id": "1",
        "name": "Criclife2",
        "logo": "https://example.com/logo.png",
        "link": "https://live6.shoq.com.pk/live/eds/Criclife2/DASH/Criclife2.mpd",
        "kid": "4301796d6d67374043c4a43c18dff7ea",
        "k": "96a3dc8766317aa169149a604928ebb6",
        "title": "Criclife2 Live Stream",
        "description": "You're Watching"
    },

    {
        "id": "2",
        "name": "willow",
        "logo": "https://example.com/logo.png",
        "link": "https://cors-proxy.cooks.fyi/https://dfwlive-v1-c1p3-sponsored.s.llnwi.net/Content/HLS.cps/Live/channel(WILLHD-3291.dfw.1080)/index.m3u8",
        "kid": "59ed8dc9d4a48857ef8e5865919496cc",
        "k": "0d3680bd8b349deda8b7fdd1da71b7f8",
        "title": "Criclife2 Live Stream",
        "description": "You're Watching"
    },

    {
        "id": "3",
        "name": "TNT",
        "logo": "https://example.com/logo.png",
        "link": "https://ottb.live.cf.ww.aiv-cdn.net/lhr-nitro/live/clients/dash/enc/wf8usag51e/out/v1/bd3b0c314fff4bb1ab4693358f3cd2d3/cenc.mpd",
        "kid": "ae26845bd33038a9c0774a0981007294",
        "k": "63ac662dde310cfb4cc6f9b43b34196d",
        "title": "TNT Live Stream",
        "description": "You're Watching"
    },
    {
        "id": "4",
        "name": "TNT2",
        "logo": "https://example.com/logo.png",
        "link": "https://ottb.live.cf.ww.aiv-cdn.net/lhr-nitro/live/clients/dash/enc/f0qvkrra8j/out/v1/f8fa17f087564f51aa4d5c700be43ec4/cenc.mpd",
        "kid": "6d1708b185c6c4d7b37600520c7cc93c",
        "k": "1aace05f58d8edef9697fd52cb09f441",
        "title": "TNT Live Stream",
        "description": "You're Watching"
    },

    {
        "id": "5",
        "name": "astro",
        "logo": "https://example.com/logo.png",
        "link": "https://dj-tm-srvr1.vercel.app/astrocric/Astro_Cricket@DJ-TM.mpd",
        "kid": "03c2e0af2f8159f9f0ce9b5dbc865f10",
        "k": "cd84ed136b0cc71f8ab8cd4d4f6a2e4c",
        "title": "TNT Live Stream",
        "description": "You're Watching"
    },

 {
        "id": "6",
        "name": "sky",
        "logo": "https://example.com/logo.png",
        "link": "https://linear-s.media.skyone.co.nz/sky-sport-2.mpd",
        "kid": "ef909acce1f53f5db2a1cdafd2e90000",
        "k": "aba1269d685f474fbddf97ce2b45c725",
        "title": "TNT Live Stream",
        "description": "You're Watching"
    },
 {
        "id": "7",
        "name": "cricbuzz1",
        "logo": "https://example.com/logo.png",
        "link": "https://uselector.cdn.intigral-ott.net/CRL2/CRL2.isml/manifest.mpd",
        "kid": "77889c7295e1f113852aa6030242b8e4",
        "k": "ec8c522d46888a15ff6533aa28ccd7f5",
        "title": "TNT Live Stream",
        "description": "You're Watching"
    },

    {
        "id": "8",
        "name": "willow",
        "logo": "https://example.com/logo.png",
        "link": " https://p-cdn1-a-cg14-linear-cbd46b77.movetv.com/clipslist/22/20250131T000000Z/20250201T000000Z.mpd",
        "kid": "N1Bt-2EVTLmZn710zkrttg",
        "k": "Z4eegMEhQisPnBEW6Wz_LQ",
        "title": "Criclife2 Live Stream",
        "description": "You're Watching"
    },
    {
        "id": "9",
        "name": "sph",
        "logo": "https://example.com/logo.png",
        "link": "https://rftv.wtf/ch.mpd?id=24",
        "kid": "24fe8f3887e0550db02ca596fd480175",
        "k": "79a62f3a5f3fa324f4de420d370a05b5",
        "title": "Criclife2 Live Stream",
        "description": "You're Watching"
    },
    {
        "id": "10",
        "name": "spe",
        "logo": "https://example.com/logo.png",
        "link": "https://bpcdncs2.dialog.lk/bpk-token/2aa@3n3xdna4v5ourqi4d3l0c0ph0apl5qv0kc23d4ba/GlobalManifest.mpd",
        "kid": "79b340b2b5f7c3c89951daabde7cdf97",
        "k": "3e22bc39d22a7f8c3516f6b58b144668",
        "title": "Criclife2 Live Stream",
        "description": "You're Watching"
    }


]
